gh_util/__init__.py
gh_util/_version.py
gh_util/api.py
gh_util/client.py
gh_util/contexts.py
gh_util/functions.py
gh_util/logging.py
gh_util/print.py
gh_util/settings.py
gh_util/types/__init__.py
gh_util/types/core.py
gh_util/types/webhooks.py
gh_util/utilities/__init__.py
gh_util/utilities/inspect.py
gh_util/utilities/process.py
gh_util/utilities/pydantic.py
gh_util-0.1.15.dist-info/METADATA
gh_util-0.1.15.dist-info/WHEEL
gh_util-0.1.15.dist-info/top_level.txt
gh_util-0.1.15.dist-info/RECORD
