Metadata-Version: 2.1
Name: gh_util
Version: 0.1.15
Summary: Minimal LLM friendly Python client for GitHub API.
Project-URL: Code, https://github.com/zzstoatzz/gh
Keywords: github,api,client,python
Classifier: Programming Language :: Python :: 3 :: Only
Classifier: Topic :: Software Development :: Libraries :: Python Modules
Requires-Python: >=3.10
Requires-Dist: devtools
Requires-Dist: httpx
Requires-Dist: jinja2
Requires-Dist: pydantic >=2.5
Requires-Dist: pydantic-settings
Requires-Dist: rich
Provides-Extra: dev
Requires-Dist: ipython ; extra == 'dev'
Requires-Dist: pre-commit <4.0,>=2.21 ; extra == 'dev'
Requires-Dist: ruff ; extra == 'dev'
